.gitignore
MANIFEST.in
README.rst
bootstrap.py
buildout.cfg
setup.py
collective/__init__.py
collective.portlet.fancyboxgallery.egg-info/PKG-INFO
collective.portlet.fancyboxgallery.egg-info/SOURCES.txt
collective.portlet.fancyboxgallery.egg-info/dependency_links.txt
collective.portlet.fancyboxgallery.egg-info/entry_points.txt
collective.portlet.fancyboxgallery.egg-info/namespace_packages.txt
collective.portlet.fancyboxgallery.egg-info/not-zip-safe
collective.portlet.fancyboxgallery.egg-info/requires.txt
collective.portlet.fancyboxgallery.egg-info/top_level.txt
collective/portlet/__init__.py
collective/portlet/fancyboxgallery/__init__.py
collective/portlet/fancyboxgallery/configure.zcml
collective/portlet/fancyboxgallery/gallery.pt
collective/portlet/fancyboxgallery/interfaces.py
collective/portlet/fancyboxgallery/portlet.pt
collective/portlet/fancyboxgallery/portlet.py
collective/portlet/fancyboxgallery/profiles/default/metadata.xml
collective/portlet/fancyboxgallery/profiles/default/portlets.xml
docs/HISTORY.txt