Metadata-Version: 1.0
Name: collective.portlet.fancyboxgallery
Version: 1.0
Summary: Gallery portlet for Plone
Home-page: https://github.com/toutpt/collective.portlet.fancyboxgallery
Author: JeanMichel FRANCOIS aka toutpt
Author-email: toutpt@gmail.com
License: GPL
Keywords: plone gallery fancybox
Platform: UNKNOWN
Classifier: Framework :: Plone :: 4.0
Classifier: Framework :: Plone :: 4.1
Classifier: Framework :: Plone :: 4.2
Classifier: Programming Language :: Python
